MANIFEST.in
README.rst
setup.py
collective/__init__.py
collective.mollie.egg-info/PKG-INFO
collective.mollie.egg-info/SOURCES.txt
collective.mollie.egg-info/dependency_links.txt
collective.mollie.egg-info/entry_points.txt
collective.mollie.egg-info/namespace_packages.txt
collective.mollie.egg-info/not-zip-safe
collective.mollie.egg-info/requires.txt
collective.mollie.egg-info/top_level.txt
collective/mollie/__init__.py
collective/mollie/adapter.py
collective/mollie/config.py
collective/mollie/configure.zcml
collective/mollie/events.py
collective/mollie/ideal.py
collective/mollie/interfaces.py
collective/mollie/testing.py
collective/mollie/version.txt
collective/mollie/xml_parser.py
collective/mollie/browser/__init__.py
collective/mollie/browser/report.py
collective/mollie/tests/__init__.py
collective/mollie/tests/browser.zcml
collective/mollie/tests/test_integration.py
collective/mollie/tests/test_unit.py
collective/mollie/tests/responses/banks.xml
collective/mollie/tests/responses/error_14.xml
collective/mollie/tests/responses/payment_cancelled.xml
collective/mollie/tests/responses/payment_cancelled_2.xml
collective/mollie/tests/responses/payment_checked_before.xml
collective/mollie/tests/responses/payment_open.xml
collective/mollie/tests/responses/payment_success.xml
collective/mollie/tests/responses/request_payment_good.xml
collective/mollie/tests/responses/request_payment_good_2.xml
collective/mollie/tests/responses/request_payment_wrong_amount.xml
collective/mollie/tests/responses/request_payment_wrong_currency.xml
collective/mollie/tests/xml/dict.xml
collective/mollie/tests/xml/dict_attributes.xml
collective/mollie/tests/xml/dict_in_dict.xml
collective/mollie/tests/xml/dict_in_list.xml
collective/mollie/tests/xml/dict_in_list_in_dict.xml
collective/mollie/tests/xml/dicts_in_dict.xml
collective/mollie/tests/xml/list.xml
collective/mollie/tests/xml/list_in_dict.xml
collective/mollie/tests/xml/list_in_list.xml
collective/mollie/tests/xml/lists_in_list.xml
collective/mollie/tests/xml/two_root_elements.xml
docs/HISTORY.txt
docs/INSTALL.txt
docs/LICENSE.GPL
docs/LICENSE.txt