Metadata-Version: 1.1
Name: collective.mollie
Version: 0.3
Summary: Wrapper for the Mollie iDeal API
Home-page: http://github.com/collective/collective.mollie
Author: Edition1
Author-email: info@edition.nl
License: GPL version 2
Keywords: ideal mollie plone
Platform: UNKNOWN
Classifier: Environment :: Web Environment
Classifier: Framework :: Plone :: 3.3
Classifier: Framework :: Plone :: 4.0
Classifier: Framework :: Plone :: 4.1
Classifier: Framework :: Plone :: 4.2
Classifier: License :: OSI Approved :: GNU General Public License (GPL)
Classifier: Operating System :: OS Independent
Classifier: Programming Language :: Python :: 2.4
Classifier: Programming Language :: Python :: 2.6
